ally_ai_llamaindex/EmbeddingModel.py
ally_ai_llamaindex/LLM.py
ally_ai_llamaindex/__init__.py
ally_ai_llamaindex-0.1.0.dist-info/LICENSE
ally_ai_llamaindex-0.1.0.dist-info/METADATA
ally_ai_llamaindex-0.1.0.dist-info/WHEEL
ally_ai_llamaindex-0.1.0.dist-info/top_level.txt
ally_ai_llamaindex-0.1.0.dist-info/RECORD
